sydeploy/__init__.py
sydeploy/errors.py
sydeploy/run.py
sydeploy/commands/__init__.py
sydeploy/commands/authenticate/__init__.py
sydeploy/commands/authenticate/aws.py
sydeploy/commands/build/__init__.py
sydeploy/commands/build/python_package.py
sydeploy/templates/meta.yaml.dist
sydeploy/templates/setup.py.dist
sydeploy/utils/__init__.py
sydeploy/utils/simple.py
sydeploy-0.3.8.dist-info/LICENSE
sydeploy-0.3.8.dist-info/METADATA
sydeploy-0.3.8.dist-info/WHEEL
sydeploy-0.3.8.dist-info/entry_points.txt
sydeploy-0.3.8.dist-info/top_level.txt
sydeploy-0.3.8.dist-info/RECORD
